attack_lookup/__init__.py
attack_lookup/__main__.py
attack_lookup/mapping.py
attack_lookup/data/v15/enterprise-attack.json
attack_lookup/data/v15/ics-attack.json
attack_lookup/data/v15/mobile-attack.json
attack_lookup-1.0.3.dist-info/LICENSE
attack_lookup-1.0.3.dist-info/METADATA
attack_lookup-1.0.3.dist-info/WHEEL
attack_lookup-1.0.3.dist-info/entry_points.txt
attack_lookup-1.0.3.dist-info/top_level.txt
attack_lookup-1.0.3.dist-info/RECORD
