Metadata-Version: 2.1
Name: attack-lookup
Version: 1.0.3
Summary: MITRE ATT&CK Lookup Tool
Home-page: https://github.com/curated-intel/attack-lookup
Author: Zander Work
Author-email: pypi@zanderwork.com
License: MIT
Classifier: License :: OSI Approved :: MIT License
Classifier: Programming Language :: Python :: 3
Classifier: Programming Language :: Python :: 3.8
Requires-Python: >=3.6
License-File: LICENSE
Requires-Dist: requests <3,>=2.22.0
Requires-Dist: stix2 ==3.0.1
